PyCurrenciesTools/__init__.py
PyCurrenciesTools/data.py
PyCurrenciesTools/errors.py
PyCurrenciesTools-1.0.2.dist-info/METADATA
PyCurrenciesTools-1.0.2.dist-info/WHEEL
PyCurrenciesTools-1.0.2.dist-info/top_level.txt
PyCurrenciesTools-1.0.2.dist-info/RECORD
