Metadata-Version: 2.1
Name: PyCurrenciesTools
Version: 1.0.2
Summary: PyCurrenciesTools is a Python library for easy currency conversion and information retrieval, providing real-time exchange rates and a comprehensive list of currency symbols and tags.
Author: oddshellnick
Author-email: oddshellnick.programming@gmail.com
Requires-Dist: PyWebRequests
